MANIFEST.in
setup.py
cmsranking2/Config.py
cmsranking2/Contest.py
cmsranking2/Entity.py
cmsranking2/Logger.py
cmsranking2/RankingWebServer.py
cmsranking2/Scoring.py
cmsranking2/Store.py
cmsranking2/Subchange.py
cmsranking2/Submission.py
cmsranking2/Task.py
cmsranking2/Team.py
cmsranking2/User.py
cmsranking2/__init__.py
cmsranking2/eventsource.py
cmsranking2/images/__init__.py
cmsranking2/images/close.svg
cmsranking2/images/face.svg
cmsranking2/images/flag.svg
cmsranking2/images/logo.svg
cmsranking2/images/tick.svg
cmsranking2/static/Chart.js
cmsranking2/static/Config.js
cmsranking2/static/DataStore.js
cmsranking2/static/HistoryStore.js
cmsranking2/static/Overview.js
cmsranking2/static/Ranking.css
cmsranking2/static/Ranking.html
cmsranking2/static/Ranking.js
cmsranking2/static/Scoreboard.js
cmsranking2/static/TeamSearch.js
cmsranking2/static/TimeView.js
cmsranking2/static/UserDetail.js
cmsranking2/static/__init__.py
cmsranking2/static/img/__init__.py
cmsranking2/static/img/close.png
cmsranking2/static/img/face.png
cmsranking2/static/img/favicon.ico
cmsranking2/static/img/flag.png
cmsranking2/static/img/logo.png
cmsranking2/static/img/tick_black.png
cmsranking2/static/img/tick_white.png
cmsranking2/static/lib/__init__.py
cmsranking2/static/lib/eventsource.js
cmsranking2/static/lib/explorercanvas.js
cmsranking2/static/lib/jquery.js
cmsranking2/static/lib/raphael.js
rws.egg-info/PKG-INFO
rws.egg-info/SOURCES.txt
rws.egg-info/dependency_links.txt
rws.egg-info/entry_points.txt
rws.egg-info/requires.txt
rws.egg-info/top_level.txt