Metadata-Version: 1.0
Name: rws
Version: 0.6.0
Summary: Ranking Web Server
Home-page: https://github.com/algorithm-ninja/rws
Author: Algorithm Ninja
Author-email: UNKNOWN
License: AGPL3
Platform: UNKNOWN
